README.md
setup.py
src/pyCAER/__init__.py
src/pyCAER/caer_communication.py
src/pyCAER/client.py
src/pyCAER/globals.py
src/pyCAER/maputils.py
src/pyCAER/utils.py
src/pyCAER.egg-info/PKG-INFO
src/pyCAER.egg-info/SOURCES.txt
src/pyCAER.egg-info/dependency_links.txt
src/pyCAER.egg-info/requires.txt
src/pyCAER.egg-info/top_level.txt
src/pyCAER/api/__init__.py
src/pyCAER/api/com_tcpclient.py
src/pyCAER/api/conf_tcpclient.py
src/pyCAER/api/mapconf_ioclient.py
test/testPerformance.py
test/testStimMon.py