Metadata-Version: 1.0
Name: pyCAER
Version: 20180208.post0
Summary: python Caer client and NCS api
Home-page: https://github.com/nmi-lab/pyCAERdynapse
Author: Emre Neftci
Author-email: eneftci@uci.edu
License: UNKNOWN
Platform: UNKNOWN
